<font>
  <info aa="1" bold="0" charset="" face="Targets_40" italic="0" outline="0" padding="2,2,2,2" size="44" smooth="1" spacing="0,0" stretchH="100" unicode=""/>
  <common base="37" lineHeight="44" packed="0" pages="1" scaleH="512" scaleW="64"/>
  <pages>
    <page file="Targets_40.png" id="0"/>
  </pages>
  <chars count="39">
    <char chnl="15" height="1" id="32" page="0" width="1" x="825" xadvance="15" xoffset="0" y="73" yoffset="43"/>
    <char chnl="15" height="42" id="33" page="0" width="10" x="563" xadvance="11" xoffset="0" y="318" yoffset="1"/>
    <char chnl="15" height="42" id="65" page="0" width="38" x="899" xadvance="39" xoffset="0" y="318" yoffset="1"/>
    <char chnl="15" height="42" id="66" page="0" width="31" x="588" xadvance="32" xoffset="0" y="859" yoffset="1"/>
    <char chnl="15" height="44" id="67" page="0" width="32" x="487" xadvance="33" xoffset="0" y="825" yoffset="0"/>
    <char chnl="15" height="42" id="68" page="0" width="31" x="920" xadvance="32" xoffset="0" y="865" yoffset="1"/>
    <char chnl="15" height="42" id="69" page="0" width="28" x="621" xadvance="29" xoffset="0" y="899" yoffset="1"/>
    <char chnl="15" height="42" id="70" page="0" width="28" x="325" xadvance="29" xoffset="0" y="884" yoffset="1"/>
    <char chnl="15" height="44" id="71" page="0" width="32" x="521" xadvance="33" xoffset="0" y="825" yoffset="0"/>
    <char chnl="15" height="42" id="72" page="0" width="31" x="751" xadvance="32" xoffset="0" y="866" yoffset="1"/>
    <char chnl="15" height="42" id="73" page="0" width="8" x="231" xadvance="9" xoffset="0" y="376" yoffset="1"/>
    <char chnl="15" height="43" id="74" page="0" width="26" x="121" xadvance="27" xoffset="0" y="939" yoffset="1"/>
    <char chnl="15" height="42" id="75" page="0" width="34" x="781" xadvance="35" xoffset="0" y="822" yoffset="1"/>
    <char chnl="15" height="42" id="76" page="0" width="28" x="35" xadvance="29" xoffset="0" y="900" yoffset="1"/>
    <char chnl="15" height="42" id="77" page="0" width="38" x="252" xadvance="39" xoffset="0" y="809" yoffset="1"/>
    <char chnl="15" height="42" id="78" page="0" width="32" x="110" xadvance="33" xoffset="0" y="857" yoffset="1"/>
    <char chnl="15" height="42" id="79" page="0" width="32" x="42" xadvance="33" xoffset="0" y="856" yoffset="1"/>
    <char chnl="15" height="42" id="80" page="0" width="31" x="177" xadvance="32" xoffset="0" y="865" yoffset="1"/>
    <char chnl="15" height="43" id="81" page="0" width="32" x="224" xadvance="33" xoffset="0" y="853" yoffset="1"/>
    <char chnl="15" height="42" id="82" page="0" width="32" x="76" xadvance="33" xoffset="0" y="857" yoffset="1"/>
    <char chnl="15" height="44" id="83" page="0" width="31" x="555" xadvance="32" xoffset="0" y="855" yoffset="0"/>
    <char chnl="15" height="42" id="84" page="0" width="30" x="449" xadvance="31" xoffset="0" y="871" yoffset="1"/>
    <char chnl="15" height="43" id="85" page="0" width="32" x="717" xadvance="33" xoffset="0" y="844" yoffset="1"/>
    <char chnl="15" height="42" id="86" page="0" width="34" x="417" xadvance="35" xoffset="0" y="825" yoffset="1"/>
    <char chnl="15" height="42" id="87" page="0" width="52" x="469" xadvance="53" xoffset="0" y="487" yoffset="1"/>
    <char chnl="15" height="42" id="88" page="0" width="34" x="907" xadvance="35" xoffset="0" y="821" yoffset="1"/>
    <char chnl="15" height="42" id="89" page="0" width="34" x="943" xadvance="35" xoffset="0" y="821" yoffset="1"/>
    <char chnl="15" height="42" id="90" page="0" width="28" x="270" xadvance="29" xoffset="0" y="899" yoffset="1"/>
    <char chnl="15" height="43" id="48" page="0" width="26" x="93" xadvance="31" xoffset="2" y="937" yoffset="0"/>
    <char chnl="15" height="42" id="49" page="0" width="16" x="153" xadvance="31" xoffset="7" y="316" yoffset="1"/>
    <char chnl="15" height="43" id="50" page="0" width="26" x="950" xadvance="31" xoffset="2" y="918" yoffset="0"/>
    <char chnl="15" height="44" id="51" page="0" width="28" x="953" xadvance="31" xoffset="1" y="872" yoffset="0"/>
    <char chnl="15" height="42" id="52" page="0" width="30" x="417" xadvance="31" xoffset="0" y="869" yoffset="1"/>
    <char chnl="15" height="43" id="53" page="0" width="26" x="843" xadvance="31" xoffset="2" y="937" yoffset="1"/>
    <char chnl="15" height="42" id="54" page="0" width="26" x="568" xadvance="31" xoffset="2" y="939" yoffset="1"/>
    <char chnl="15" height="42" id="55" page="0" width="27" x="983" xadvance="31" xoffset="1" y="917" yoffset="1"/>
    <char chnl="15" height="43" id="56" page="0" width="28" x="366" xadvance="31" xoffset="1" y="875" yoffset="1"/>
    <char chnl="15" height="43" id="57" page="0" width="26" x="687" xadvance="31" xoffset="2" y="933" yoffset="0"/>
    <char chnl="15" height="26" id="58" page="0" width="9" x="468" xadvance="10" xoffset="0" y="138" yoffset="13"/>
  </chars>
  <kernings count="0"/>
</font>
