{"frames": {

"0bg_garage0000":
{
	"frame": {"x":2,"y":2,"w":720,"h":480},
	"rotated": false,
	"trimmed": false,
	"spriteSourceSize": {"x":0,"y":0,"w":720,"h":480},
	"sourceSize": {"w":720,"h":480}
},
"0bg_garage_l0000":
{
	"frame": {"x":329,"y":922,"w":30,"h":480},
	"rotated": false,
	"trimmed": false,
	"spriteSourceSize": {"x":0,"y":0,"w":30,"h":480},
	"sourceSize": {"w":30,"h":480}
},
"0bg_garage_r0000":
{
	"frame": {"x":361,"y":922,"w":30,"h":480},
	"rotated": false,
	"trimmed": false,
	"spriteSourceSize": {"x":0,"y":0,"w":30,"h":480},
	"sourceSize": {"w":30,"h":480}
},
"0logo0000":
{
	"frame": {"x":724,"y":2,"w":198,"h":325},
	"rotated": false,
	"trimmed": false,
	"spriteSourceSize": {"x":0,"y":0,"w":198,"h":325},
	"sourceSize": {"w":198,"h":325}
},
"0popup_bg0000":
{
	"frame": {"x":2,"y":484,"w":680,"h":436},
	"rotated": false,
	"trimmed": false,
	"spriteSourceSize": {"x":0,"y":0,"w":680,"h":436},
	"sourceSize": {"w":680,"h":436}
},
"InGameMusicButton0000":
{
	"frame": {"x":599,"y":922,"w":53,"h":44},
	"rotated": false,
	"trimmed": false,
	"spriteSourceSize": {"x":0,"y":0,"w":53,"h":44},
	"sourceSize": {"w":53,"h":44}
},
"InGameMusicButton0001":
{
	"frame": {"x":473,"y":1109,"w":53,"h":44},
	"rotated": false,
	"trimmed": false,
	"spriteSourceSize": {"x":0,"y":0,"w":53,"h":44},
	"sourceSize": {"w":53,"h":44}
},
"InGameMusicButton0002":
{
	"frame": {"x":393,"y":1118,"w":53,"h":44},
	"rotated": false,
	"trimmed": false,
	"spriteSourceSize": {"x":0,"y":0,"w":53,"h":44},
	"sourceSize": {"w":53,"h":44}
},
"InGamePauseButton0000":
{
	"frame": {"x":291,"y":1056,"w":33,"h":49},
	"rotated": false,
	"trimmed": false,
	"spriteSourceSize": {"x":0,"y":0,"w":33,"h":49},
	"sourceSize": {"w":33,"h":49}
},
"LeveMapItemLocked0000":
{
	"frame": {"x":589,"y":1025,"w":63,"h":79},
	"rotated": false,
	"trimmed": false,
	"spriteSourceSize": {"x":0,"y":0,"w":63,"h":79},
	"sourceSize": {"w":63,"h":79}
},
"LeveMapItemLocked0001":
{
	"frame": {"x":654,"y":1025,"w":63,"h":79},
	"rotated": false,
	"trimmed": false,
	"spriteSourceSize": {"x":0,"y":0,"w":63,"h":79},
	"sourceSize": {"w":63,"h":79}
},
"LeveMapItemLocked0002":
{
	"frame": {"x":719,"y":1043,"w":63,"h":79},
	"rotated": false,
	"trimmed": false,
	"spriteSourceSize": {"x":0,"y":0,"w":63,"h":79},
	"sourceSize": {"w":63,"h":79}
},
"LeveMapItemLocked0003":
{
	"frame": {"x":784,"y":1043,"w":63,"h":79},
	"rotated": false,
	"trimmed": false,
	"spriteSourceSize": {"x":0,"y":0,"w":63,"h":79},
	"sourceSize": {"w":63,"h":79}
},
"LeveMapItemLocked0004":
{
	"frame": {"x":849,"y":1043,"w":63,"h":79},
	"rotated": false,
	"trimmed": false,
	"spriteSourceSize": {"x":0,"y":0,"w":63,"h":79},
	"sourceSize": {"w":63,"h":79}
},
"LeveMapItemLocked0005":
{
	"frame": {"x":914,"y":1043,"w":63,"h":79},
	"rotated": false,
	"trimmed": false,
	"spriteSourceSize": {"x":0,"y":0,"w":63,"h":79},
	"sourceSize": {"w":63,"h":79}
},
"arrow_btn0000":
{
	"frame": {"x":179,"y":1056,"w":54,"h":86},
	"rotated": false,
	"trimmed": false,
	"spriteSourceSize": {"x":0,"y":0,"w":54,"h":86},
	"sourceSize": {"w":54,"h":86}
},
"arrow_btn0001":
{
	"frame": {"x":235,"y":1056,"w":54,"h":86},
	"rotated": false,
	"trimmed": false,
	"spriteSourceSize": {"x":0,"y":0,"w":54,"h":86},
	"sourceSize": {"w":54,"h":86}
},
"arrow_key0000":
{
	"frame": {"x":393,"y":1053,"w":78,"h":63},
	"rotated": false,
	"trimmed": false,
	"spriteSourceSize": {"x":0,"y":0,"w":78,"h":63},
	"sourceSize": {"w":78,"h":63}
},
"arrow_key20000":
{
	"frame": {"x":82,"y":1101,"w":83,"h":53},
	"rotated": false,
	"trimmed": false,
	"spriteSourceSize": {"x":0,"y":0,"w":83,"h":53},
	"sourceSize": {"w":83,"h":53}
},
"bg0000":
{
	"frame": {"x":724,"y":467,"w":10,"h":10},
	"rotated": false,
	"trimmed": false,
	"spriteSourceSize": {"x":0,"y":0,"w":10,"h":10},
	"sourceSize": {"w":10,"h":10}
},
"black0000":
{
	"frame": {"x":979,"y":1075,"w":40,"h":40},
	"rotated": false,
	"trimmed": false,
	"spriteSourceSize": {"x":0,"y":0,"w":40,"h":40},
	"sourceSize": {"w":40,"h":40}
},
"btn_body0000":
{
	"frame": {"x":924,"y":2,"w":96,"h":96},
	"rotated": false,
	"trimmed": false,
	"spriteSourceSize": {"x":0,"y":0,"w":96,"h":96},
	"sourceSize": {"w":96,"h":96}
},
"btn_body0001":
{
	"frame": {"x":924,"y":2,"w":96,"h":96},
	"rotated": false,
	"trimmed": false,
	"spriteSourceSize": {"x":0,"y":0,"w":96,"h":96},
	"sourceSize": {"w":96,"h":96}
},
"btn_credits0000":
{
	"frame": {"x":628,"y":1106,"w":62,"h":60},
	"rotated": false,
	"trimmed": false,
	"spriteSourceSize": {"x":0,"y":0,"w":62,"h":60},
	"sourceSize": {"w":62,"h":60}
},
"en0000":
{
	"frame": {"x":867,"y":975,"w":96,"h":66},
	"rotated": false,
	"trimmed": false,
	"spriteSourceSize": {"x":0,"y":0,"w":96,"h":66},
	"sourceSize": {"w":96,"h":66}
},
"es0000":
{
	"frame": {"x":924,"y":254,"w":96,"h":66},
	"rotated": false,
	"trimmed": false,
	"spriteSourceSize": {"x":0,"y":0,"w":96,"h":66},
	"sourceSize": {"w":96,"h":66}
},
"exit_btn0000":
{
	"frame": {"x":924,"y":100,"w":92,"h":80},
	"rotated": false,
	"trimmed": false,
	"spriteSourceSize": {"x":0,"y":0,"w":92,"h":80},
	"sourceSize": {"w":92,"h":80}
},
"fr0000":
{
	"frame": {"x":393,"y":985,"w":96,"h":66},
	"rotated": false,
	"trimmed": false,
	"spriteSourceSize": {"x":0,"y":0,"w":96,"h":66},
	"sourceSize": {"w":96,"h":66}
},
"improved_bg0000":
{
	"frame": {"x":724,"y":329,"w":153,"h":136},
	"rotated": false,
	"trimmed": false,
	"spriteSourceSize": {"x":0,"y":0,"w":153,"h":136},
	"sourceSize": {"w":153,"h":136}
},
"it0000":
{
	"frame": {"x":769,"y":975,"w":96,"h":66},
	"rotated": false,
	"trimmed": false,
	"spriteSourceSize": {"x":0,"y":0,"w":96,"h":66},
	"sourceSize": {"w":96,"h":66}
},
"logo_mad0000":
{
	"frame": {"x":684,"y":484,"w":305,"h":404},
	"rotated": false,
	"trimmed": false,
	"spriteSourceSize": {"x":0,"y":0,"w":305,"h":404},
	"sourceSize": {"w":305,"h":404}
},
"next_btn0000":
{
	"frame": {"x":100,"y":1023,"w":77,"h":76},
	"rotated": false,
	"trimmed": false,
	"spriteSourceSize": {"x":0,"y":0,"w":77,"h":76},
	"sourceSize": {"w":77,"h":76}
},
"nl0000":
{
	"frame": {"x":491,"y":985,"w":96,"h":66},
	"rotated": false,
	"trimmed": false,
	"spriteSourceSize": {"x":0,"y":0,"w":96,"h":66},
	"sourceSize": {"w":96,"h":66}
},
"orange_btn0000":
{
	"frame": {"x":2,"y":922,"w":192,"h":99},
	"rotated": false,
	"trimmed": false,
	"spriteSourceSize": {"x":0,"y":0,"w":192,"h":99},
	"sourceSize": {"w":192,"h":99}
},
"orange_btn_big0000":
{
	"frame": {"x":684,"y":890,"w":327,"h":83},
	"rotated": false,
	"trimmed": false,
	"spriteSourceSize": {"x":0,"y":0,"w":327,"h":83},
	"sourceSize": {"w":327,"h":83}
},
"pause_bg0000":
{
	"frame": {"x":473,"y":1053,"w":89,"h":54},
	"rotated": false,
	"trimmed": false,
	"spriteSourceSize": {"x":0,"y":0,"w":89,"h":54},
	"sourceSize": {"w":89,"h":54}
},
"play_btn0000":
{
	"frame": {"x":564,"y":1106,"w":62,"h":65},
	"rotated": false,
	"trimmed": false,
	"spriteSourceSize": {"x":0,"y":0,"w":62,"h":65},
	"sourceSize": {"w":62,"h":65}
},
"pt0000":
{
	"frame": {"x":2,"y":1023,"w":96,"h":66},
	"rotated": false,
	"trimmed": false,
	"spriteSourceSize": {"x":0,"y":0,"w":96,"h":66},
	"sourceSize": {"w":96,"h":66}
},
"restart_btn0000":
{
	"frame": {"x":965,"y":975,"w":45,"h":52},
	"rotated": false,
	"trimmed": false,
	"spriteSourceSize": {"x":0,"y":0,"w":45,"h":52},
	"sourceSize": {"w":45,"h":52}
},
"select_level0000":
{
	"frame": {"x":924,"y":182,"w":94,"h":70},
	"rotated": false,
	"trimmed": false,
	"spriteSourceSize": {"x":0,"y":0,"w":94,"h":70},
	"sourceSize": {"w":94,"h":70}
},
"shop_btn0000":
{
	"frame": {"x":2,"y":1091,"w":78,"h":57},
	"rotated": false,
	"trimmed": false,
	"spriteSourceSize": {"x":0,"y":0,"w":78,"h":57},
	"sourceSize": {"w":78,"h":57}
},
"star00000":
{
	"frame": {"x":879,"y":329,"w":137,"h":138},
	"rotated": false,
	"trimmed": false,
	"spriteSourceSize": {"x":0,"y":0,"w":137,"h":138},
	"sourceSize": {"w":137,"h":138}
},
"star10000":
{
	"frame": {"x":196,"y":922,"w":131,"h":132},
	"rotated": false,
	"trimmed": false,
	"spriteSourceSize": {"x":0,"y":0,"w":131,"h":132},
	"sourceSize": {"w":131,"h":132}
},
"timer_bg0000":
{
	"frame": {"x":599,"y":975,"w":168,"h":48},
	"rotated": false,
	"trimmed": false,
	"spriteSourceSize": {"x":0,"y":0,"w":168,"h":48},
	"sourceSize": {"w":168,"h":48}
},
"top_bg0000":
{
	"frame": {"x":393,"y":922,"w":204,"h":61},
	"rotated": false,
	"trimmed": false,
	"spriteSourceSize": {"x":0,"y":0,"w":204,"h":61},
	"sourceSize": {"w":204,"h":61}
},
"w_star0000":
{
	"frame": {"x":979,"y":1029,"w":40,"h":44},
	"rotated": false,
	"trimmed": false,
	"spriteSourceSize": {"x":0,"y":0,"w":40,"h":44},
	"sourceSize": {"w":40,"h":44}
}},
"meta": {
	"app": "Adobe Flash Professional",
	"version": "15.0.1.179",
	"image": "garage.png",
	"format": "RGBA8888",
	"size": {"w":1024,"h":2048},
	"scale": "1"
}
}
